hackkk/__init__.py
hackkk/courses.py
hackkk/utils.py
hackkk-0.5.1.dist-info/METADATA
hackkk-0.5.1.dist-info/WHEEL
hackkk-0.5.1.dist-info/top_level.txt
hackkk-0.5.1.dist-info/RECORD
