Metadata-Version: 2.1
Name: hackkk
Version: 0.5.1
Summary: Una biblioteca para consultar cursos de hack4u.
Home-page: https://hack4u.io
Author: Marcelo Vázquez
